{"Tags":"ZCR","Names":[{"Text":"Afdranz","Lang":"zh"}],"Credits":[],"X":-7,"Y":-95,"Products":[],"DataFile":{"Author":"Clifford Linehan","Source":"Zhodani Core Route Project","Milieu":"M1105","Ref":"https:\/\/web.archive.org\/web\/20050828212346\/http:\/\/www.geocities.com\/traveller_core_route\/proj001\/proj001.html"},"Subsectors":[{"Name":"Ploblmenzh","Index":"A","IndexNumber":0},{"Name":"Ientsfrech","Index":"B","IndexNumber":1},{"Name":"Nzhrtsa","Index":"C","IndexNumber":2},{"Name":"Vlepia","Index":"D","IndexNumber":3},{"Name":"Yedltsoze","Index":"E","IndexNumber":4},{"Name":"Niavrtliak","Index":"F","IndexNumber":5},{"Name":"Ncheshzekr","Index":"G","IndexNumber":6},{"Name":"Sanjchiazhats","Index":"H","IndexNumber":7},{"Name":"Nienjtsatsich","Index":"I","IndexNumber":8},{"Name":"Brafbrenchizh","Index":"J","IndexNumber":9},{"Name":"Nefrtsifrjie","Index":"K","IndexNumber":10},{"Name":"Sianzhnzatle","Index":"L","IndexNumber":11},{"Name":"Nzovlziaf","Index":"M","IndexNumber":12},{"Name":"Fetsfablifl","Index":"N","IndexNumber":13},{"Name":"Jdiabriea","Index":"O","IndexNumber":14},{"Name":"Zeanzh","Index":"P","IndexNumber":15}],"Allegiances":[{"Name":"Non-Aligned, Human-dominated","Code":"Na","Base":"Na"},{"Name":"Zhodani Client","Code":"Zc"}],"Labels":[],"Borders":[],"Regions":[],"Routes":[{"Start":"0923","End":"1024","Type":"Core Route"},{"Start":"0923","End":"1120","Type":"Core Route"},{"Start":"1024","End":"1425","Type":"Core Route"},{"Start":"1120","End":"1216","Type":"Core Route"},{"Start":"1216","End":"1514","Type":"Core Route"},{"Start":"1425","End":"1529","Type":"Core Route"},{"Start":"1514","End":"1912","Type":"Core Route"},{"Start":"1529","End":"1533","Type":"Core Route"},{"Start":"1533","End":"1636","Type":"Core Route"},{"Start":"1636","End":"1936","Type":"Core Route"},{"Start":"1806","End":"1809","Type":"Core Route"},{"Start":"1806","End":"2204","Type":"Core Route"},{"Start":"1809","End":"1912","Type":"Core Route"},{"Start":"1936","End":"2038","Type":"Core Route"},{"Start":"2038","End":"2102","EndOffsetY":1,"Type":"Core Route"},{"Start":"2102","End":"2139","EndOffsetY":-1,"Type":"Core Route"},{"Start":"2102","End":"2204","Type":"Core Route"}]}