{"Tags":"ZCR","Names":[{"Text":"Azaz","Lang":"zh"}],"Credits":[],"X":-7,"Y":-76,"Products":[],"DataFile":{"Author":"Clifford Linehan","Source":"Zhodani Core Route Project","Milieu":"M1105","Ref":"https:\/\/web.archive.org\/web\/20050828212346\/http:\/\/www.geocities.com\/traveller_core_route\/proj001\/proj001.html"},"Subsectors":[{"Name":"Frazfechvli","Index":"A","IndexNumber":0},{"Name":"Ninshnshia'vlen","Index":"B","IndexNumber":1},{"Name":"Afliash","Index":"C","IndexNumber":2},{"Name":"Shavrflechieb","Index":"D","IndexNumber":3},{"Name":"Iefrins","Index":"E","IndexNumber":4},{"Name":"Ienjonzh","Index":"F","IndexNumber":5},{"Name":"Renjachiaz","Index":"G","IndexNumber":6},{"Name":"Iazh","Index":"H","IndexNumber":7},{"Name":"Najplazdlim","Index":"I","IndexNumber":8},{"Name":"Ziepialrinj","Index":"J","IndexNumber":9},{"Name":"Nefblakli","Index":"K","IndexNumber":10},{"Name":"Dlevrnjabrchi","Index":"L","IndexNumber":11},{"Name":"Blaklie","Index":"M","IndexNumber":12},{"Name":"Chtiebrfrotsbre","Index":"N","IndexNumber":13},{"Name":"Zieflievrench","Index":"O","IndexNumber":14},{"Name":"Plijianch","Index":"P","IndexNumber":15}],"Allegiances":[{"Name":"Non-Aligned, Human-dominated","Code":"Na","Base":"Na"},{"Name":"Zhodani Client","Code":"Zc"}],"Labels":[],"Borders":[],"Regions":[],"Routes":[{"Start":"1327","End":"1430","Type":"Core Route"},{"Start":"1327","End":"1524","Type":"Core Route"},{"Start":"1338","End":"1434","Type":"Core Route"},{"Start":"1338","End":"1740","Type":"Core Route"},{"Start":"1430","End":"1434","Type":"Core Route"},{"Start":"1521","End":"1524","Type":"Core Route"},{"Start":"1521","End":"1719","Type":"Core Route"},{"Start":"1615","End":"1713","Type":"Core Route"},{"Start":"1615","End":"1719","Type":"Core Route"},{"Start":"1713","End":"1809","Type":"Core Route"},{"Start":"1740","End":"1801","EndOffsetY":1,"Type":"Core Route"},{"Start":"1802","End":"1906","Type":"Core Route"},{"Start":"1802","End":"1939","EndOffsetY":-1,"Type":"Core Route"},{"Start":"1809","End":"1906","Type":"Core Route"}]}