{"Tags":"Faraway DistantFringe","Names":[{"Text":"Kalash"}],"Credits":[],"X":58,"Y":27,"Products":[],"DataFile":{"Milieu":"M1105"},"Subsectors":[],"Allegiances":[{"Name":"Non-aligned, unclaimed","Code":"Nx"}],"Labels":[{"Hex":"1806","Color":"Gray","Wrap":false,"Text":"Stiletto Void"},{"Hex":"1219","Color":"Gray","Wrap":false,"Text":"Kalash Basin"},{"Hex":"2514","Color":"Gray","Size":"large","Wrap":false,"Text":"Empty Reach"},{"Hex":"1227","Color":"Gray","Wrap":false,"Text":"Langeflach Rift"},{"Hex":"2237","Color":"Gray","Wrap":false,"Text":"The Straights"}],"Borders":[],"Regions":[{"Color":"Plum","LabelPosition":"2221","Label":"Laurent's Reef","Path":"2927 3026 3126 3225 3224 3223 3222 3322 3321 3320 3321 3322 3323 3324 3325 3326 3327 3328 3329 3330 3230 3131 3130 3129 3028 2928 2927"},{"Color":"Plum","LabelPosition":"3128","Label":"Long Reef","Path":"1920 2019 2120 2219 2319 2320 2420 2421 2422 2323 2223 2124 2123 2122 2021 1921 1920"}],"Routes":[]}