{"Tags":"OTU","Abbreviation":"Malo","Names":[{"Text":"Malorn"}],"Credits":[],"X":0,"Y":5,"Products":[],"DataFile":{"Author":"CORE","Source":"The Zhodani Base","Milieu":"M1105","Ref":"http:\/\/zho.berka.com\/data\/CLASSIC\/sector.pl?sector=MALORN"},"Subsectors":[{"Name":"Malorn","Index":"A","IndexNumber":0},{"Name":"Maiste","Index":"B","IndexNumber":1},{"Name":"Heiligebet","Index":"C","IndexNumber":2},{"Name":"Oberer","Index":"D","IndexNumber":3},{"Name":"Frankfurt","Index":"E","IndexNumber":4},{"Name":"Amorine","Index":"F","IndexNumber":5},{"Name":"Volxenke","Index":"G","IndexNumber":6},{"Name":"Geheim","Index":"H","IndexNumber":7},{"Name":"Gesetz","Index":"I","IndexNumber":8},{"Name":"Lords","Index":"J","IndexNumber":9},{"Name":"Toh","Index":"K","IndexNumber":10},{"Name":"Attacotti","Index":"L","IndexNumber":11},{"Name":"Kiel","Index":"M","IndexNumber":12},{"Name":"Ustov","Index":"N","IndexNumber":13},{"Name":"Saar","Index":"O","IndexNumber":14},{"Name":"Terese","Index":"P","IndexNumber":15}],"Allegiances":[{"Name":"Malorn Union","Code":"Mu"},{"Name":"Non-Aligned, Human-dominated","Code":"Na","Base":"Na"},{"Name":"Lords of Vision","Code":"Lv"},{"Name":"Great Terbah","Code":"Gt"},{"Name":"Toh Republic","Code":"Tr"},{"Name":"Joie De Vivre","Code":"Jd"},{"Name":"Bright Star Cooperate","Code":"Bs"},{"Name":"Daprolix Juncture of Suns","Code":"Dj"},{"Name":"Parity of Brothers","Code":"Pb"},{"Name":"Creation of Nonpareil","Code":"Cn"}],"Labels":[],"Borders":[{"Color":"Green","Allegiance":"Bs","LabelPosition":"2723","Path":"2520 2620 2721 2821 2722 2723 2724 2725 2624 2623 2523 2522 2521 2520"},{"Color":"Purple","Allegiance":"Cn","LabelPosition":"3221","Path":"3121 3220 3320 3321 3322 3221 3121"},{"Color":"OliveDrab","Allegiance":"Dj","LabelPosition":"3026","Path":"2926 3026 3126 3125 3126 3026 2926"},{"Color":"Lime","Allegiance":"Gt","LabelPosition":"2111","Path":"1508 1607 1708 1808 1909 2009 2109 2208 2309 2409 2510 2610 2611 2612 2613 2614 2514 2513 2512 2411 2312 2212 2213 2113 2013 1913 1812 1712 1611 1610 1510 1509 1508"},{"Color":"Blue","Allegiance":"Jd","LabelPosition":"1918","Path":"1817 1917 2017 2018 2019 2018 1918 1817"},{"Color":"Cyan","Allegiance":"Lv","LabelPosition":"1125","Path":"0923 0924 1024 1025 1126 1226 1227 1127 1126 1025 0925 0924 0923"},{"Color":"White","Allegiance":"Mu","LabelPosition":"0604","Path":"0000 0100 0200 0300 0400 0500 0501 0502 0503 0603 0704 0804 0905 1005 1105 1204 1205 1106 1107 1108 1007 0907 0806 0707 0607 0508 0407 0308 0208 0108 0007 0006 0005 0004 0003 0002 0001 0000"},{"Color":"Brown","Allegiance":"Pb","LabelPosition":"3214","Path":"3115 3214 3213 3214 3315 3214 3115"},{"Color":"HotPink","Allegiance":"Tr","LabelPosition":"2026","Path":"1727 1826 1926 2025 2125 2224 2325 2225 2126 2026 1927 1827 1828 1827 1727"}],"Regions":[],"Routes":[]}