{"Tags":"ZCR","Names":[{"Text":"Prinjobliedl","Lang":"zh"}],"Credits":[],"X":-7,"Y":-13,"Products":[],"DataFile":{"Author":"Clifford Linehan","Source":"Zhodani Core Route Project","Milieu":"M1105","Ref":"https:\/\/web.archive.org\/web\/20050828212346\/http:\/\/www.geocities.com\/traveller_core_route\/proj001\/proj001.html"},"Subsectors":[{"Name":"Iao","Index":"A","IndexNumber":0},{"Name":"Atsach","Index":"B","IndexNumber":1},{"Name":"Iaia","Index":"C","IndexNumber":2},{"Name":"Braplloia","Index":"D","IndexNumber":3},{"Name":"Iafpranch","Index":"E","IndexNumber":4},{"Name":"Klablebrdofr","Index":"F","IndexNumber":5},{"Name":"Shachied","Index":"G","IndexNumber":6},{"Name":"Kraklnshiants","Index":"H","IndexNumber":7},{"Name":"Klifabrshezh","Index":"I","IndexNumber":8},{"Name":"Zhielrvriez","Index":"J","IndexNumber":9},{"Name":"Flanchpra","Index":"K","IndexNumber":10},{"Name":"Zhdazheda","Index":"L","IndexNumber":11},{"Name":"Aia","Index":"M","IndexNumber":12},{"Name":"Fiakprefr","Index":"N","IndexNumber":13},{"Name":"Shireblef","Index":"O","IndexNumber":14},{"Name":"Chtadleble","Index":"P","IndexNumber":15}],"Allegiances":[{"Name":"Non-Aligned, Human-dominated","Code":"Na","Base":"Na"},{"Name":"Zhodani Consulate","Code":"Zh","Base":"Zh"},{"Name":"Zhodani Client","Code":"Zc"},{"Name":"Droyne","Code":"Dr"}],"Labels":[],"Borders":[{"Allegiance":"ZhVQ","LabelPosition":"1432","Path":"0836 0936 1035 1135 1134 1133 1132 1131 1130 1129 1128 1127 1128 1129 1130 1131 1231 1332 1432 1533 1633 1734 1834 1935 1834 1734 1633 1533 1433 1334 1234 1135 1035 0936 0836"},{"Allegiance":"ZhVQ","LabelPosition":"1917","Path":"1314 1414 1515 1614 1715 1814 1915 2015 2116 2216 2316 2416 2517 2416 2316 2216 2117 2016 1917 1918 1919 2019 1920 1819 1818 1718 1618 1519 1419 1420 1320 1419 1519 1618 1718 1717 1716 1615 1515 1414 1314"},{"ShowLabel":false,"Allegiance":"ZhVQ","LabelPosition":"1439","Path":"1338 1438 1439 1438 1338"},{"ShowLabel":false,"Allegiance":"ZhVQ","LabelPosition":"0621","Path":"0621"},{"ShowLabel":false,"Allegiance":"ZhVQ","LabelPosition":"0712","Path":"0712"},{"ShowLabel":false,"Allegiance":"ZhVQ","LabelPosition":"0824","Path":"0824"},{"ShowLabel":false,"Allegiance":"ZhVQ","LabelPosition":"0914","Path":"0914"},{"ShowLabel":false,"Allegiance":"ZhVQ","LabelPosition":"1020","Path":"1020"},{"ShowLabel":false,"Allegiance":"ZhVQ","LabelPosition":"1117","Path":"1117"},{"ShowLabel":false,"Allegiance":"ZhVQ","LabelPosition":"1223","Path":"1223"},{"ShowLabel":false,"Allegiance":"ZhVQ","LabelPosition":"1904","Path":"1904"},{"ShowLabel":false,"Allegiance":"ZhVQ","LabelPosition":"1911","Path":"1911"},{"ShowLabel":false,"Allegiance":"ZhVQ","LabelPosition":"2007","Path":"2007"},{"ShowLabel":false,"Allegiance":"ZhVQ","LabelPosition":"2335","Path":"2335"},{"ShowLabel":false,"Allegiance":"ZhVQ","LabelPosition":"2817","Path":"2817"}],"Regions":[],"Routes":[{"Start":"0621","End":"0824","Allegiance":"ZhCo"},{"Start":"0621","End":"1020","Allegiance":"ZhCo"},{"Start":"0712","End":"0914","Allegiance":"ZhCo"},{"Start":"0824","End":"1127","Allegiance":"ZhCo"},{"Start":"0836","End":"1135","Allegiance":"ZhCo"},{"Start":"0914","End":"1117","Allegiance":"ZhCo"},{"Start":"0914","End":"1314","Allegiance":"ZhCo"},{"Start":"1020","End":"1320","Allegiance":"ZhCo"},{"Start":"1117","End":"1320","Allegiance":"ZhCo"},{"Start":"1127","End":"1131","Type":"Core Route"},{"Start":"1127","End":"1223","Type":"Core Route"},{"Start":"1131","End":"1135","Type":"Core Route"},{"Start":"1131","End":"1533","Allegiance":"ZhCo"},{"Start":"1135","End":"1338","Type":"Core Route"},{"Start":"1135","End":"1533","Allegiance":"ZhCo"},{"Start":"1223","End":"1420","Type":"Core Route"},{"Start":"1314","End":"1614","Allegiance":"ZhCo"},{"Start":"1320","End":"1420","Allegiance":"ZhCo"},{"Start":"1338","End":"1439","Type":"Core Route"},{"Start":"1420","End":"1718","Type":"Core Route"},{"Start":"1439","End":"1403","EndOffsetY":1,"Type":"Core Route"},{"Start":"1533","End":"1935","Allegiance":"ZhCo"},{"Start":"1614","End":"1718","Allegiance":"ZhCo"},{"Start":"1614","End":"1814","Allegiance":"ZhCo"},{"Start":"1718","End":"1814","Type":"Core Route"},{"Start":"1718","End":"1920","Allegiance":"ZhCo"},{"Start":"1718","End":"2117","Allegiance":"ZhCo"},{"Start":"1814","End":"1911","Type":"Core Route"},{"Start":"1814","End":"2117","Allegiance":"ZhCo"},{"Start":"1904","End":"2007","Type":"Core Route"},{"Start":"1904","End":"2040","EndOffsetY":-1,"Type":"Core Route"},{"Start":"1911","End":"2007","Type":"Core Route"},{"Start":"1935","End":"2335","Allegiance":"ZhCo"},{"Start":"2117","End":"2517","Allegiance":"ZhCo"},{"Start":"2517","End":"2817","Allegiance":"ZhCo"},{"Start":"2817","End":"3016","Allegiance":"ZhCo"},{"Start":"2817","End":"3017","Allegiance":"ZhCo"},{"Start":"3016","End":"3017","Allegiance":"ZhCo"}]}