{"Tags":"Faraway DistantFringe","Names":[{"Text":"Range"}],"Credits":[],"X":57,"Y":26,"Products":[],"DataFile":{"Milieu":"M1105"},"Subsectors":[],"Allegiances":[{"Name":"Non-aligned, unclaimed","Code":"Nx"}],"Labels":[{"Hex":"1312","Color":"Gray","Wrap":false,"Text":"Desolate Space"},{"Hex":"2025","Color":"Gray","Size":"large","Wrap":false,"Text":"Basilisk Rift"},{"Hex":"2233","Color":"Gray","Wrap":false,"Text":"Wrongshore"}],"Borders":[],"Regions":[{"Color":"DarkBlue","LabelPosition":"0516","Label":"Hawk Cloud","Path":"0216 0316 0416 0516 0515 0414 0413 0514 0614 0715 0814 0914 1014 0914 0814 0715 0716 0616 0617 0718 0617 0517 0417 0317 0216"}],"Routes":[]}