{"Tags":"OTU","Abbreviation":"Ruth","Names":[{"Text":"Ruthless Veil"}],"Credits":[],"X":0,"Y":7,"Products":[],"DataFile":{"Author":"Miles A. Maria","Milieu":"M1105"},"Subsectors":[{"Name":"Malmori","Index":"A","IndexNumber":0},{"Name":"Abraxas","Index":"B","IndexNumber":1},{"Name":"Adams","Index":"C","IndexNumber":2},{"Name":"Asogainz","Index":"D","IndexNumber":3},{"Name":"Primaris","Index":"E","IndexNumber":4},{"Name":"Onvinda","Index":"F","IndexNumber":5},{"Name":"Enkadus","Index":"G","IndexNumber":6},{"Name":"Tara","Index":"H","IndexNumber":7},{"Name":"Woldyhool","Index":"I","IndexNumber":8},{"Name":"Zanak","Index":"J","IndexNumber":9},{"Name":"Nagor","Index":"K","IndexNumber":10},{"Name":"Reblais","Index":"L","IndexNumber":11},{"Name":"Upholla","Index":"M","IndexNumber":12},{"Name":"Seanerth","Index":"N","IndexNumber":13},{"Name":"Soverign","Index":"O","IndexNumber":14},{"Name":"Xandarz","Index":"P","IndexNumber":15}],"Allegiances":[{"Name":"Non-Aligned, Human-dominated","Code":"Na","Base":"Na"},{"Name":"Mining Protectorate","Code":"Mp"},{"Name":"Abraxan Territories","Code":"At"},{"Name":"Soverign Dominate","Code":"Sd"},{"Name":"Bellus Frontier District","Code":"Bd"},{"Name":"Reblais Confederation","Code":"Rc"}],"Stylesheet":"\n    border.At { color: purple; style: dotted }\n    border.Bd { color: blue }\n    border.Mp { color: green; style: dotted }\n    border.Rc { color: green; style: dotted }\n    border.Sd { color: violet; style: dotted }\n  ","Labels":[],"Borders":[{"Allegiance":"At","LabelPosition":"1107","Path":"0904 1003 1104 1204 1205 1206 1207 1107 1006 0906 0905 0904"},{"Allegiance":"Bd","LabelPosition":"2105","Path":"1505 1604 1603 1602 1702 1802 1902 2001 2101 2201 2302 2402 2403 2404 2305 2204 2105 2004 1905 1906 1806 1707 1606 1506 1505"},{"Allegiance":"Mp","LabelPosition":"0511","Path":"0206 0306 0406 0507 0607 0707 0807 0808 0909 1009 1010 1011 0912 0812 0712 0611 0511 0410 0310 0309 0208 0207 0206"},{"Allegiance":"Rc","LabelPosition":"2024","Path":"2022 2122 2222 2323 2423 2424 2525 2526 2426 2326 2225 2125 2124 2023 2022"},{"Allegiance":"Sd","LabelPosition":"1636","Path":"1535 1634 1735 1736 1737 1738 1637 1537 1536 1535"}],"Regions":[{"Color":"Red","LabelPosition":"2532","Label":"Quinn's Nebula","Path":"1732 1831 1931 2030 2029 2129 2128 2027 2026 2126 2226 2326 2426 2427 2428 2429 2430 2531 2631 2731 2830 2930 3030 3131 3031 3032 3133 3134 3234 3235 3136 3036 3037 3138 3238 3239 3139 3038 2938 2937 2836 2736 2636 2637 2738 2739 2638 2539 2439 2440 2340 2439 2438 2338 2237 2137 2036 1937 1836 1936 2036 2136 2135 2034 1934 1833 1733 1732"},{"Color":"Red","LabelPosition":"2825","Path":"2421 2522 2621 2722 2821 2820 2921 2821 2822 2823 2924 3024 3124 3223 3224 3225 3126 3127 3128 3028 3029 2930 2829 2828 2728 2628 2627 2626 2625 2624 2524 2523 2522 2421"},{"Color":"Red","LabelPosition":"3031","Path":"3031"},{"Color":"Red","LabelPosition":"2737","Path":"2636 2737 2837 2737 2637 2636"},{"Color":"Red","LabelPosition":"2133","Path":"1933 2032 2031 2131 2132 2232 2233 2234 2335 2234 2134 2033 1933"},{"Color":"Red","LabelPosition":"3034","Path":"2935 3034 3033 3034 3135 3034 2935"},{"Color":"Red","LabelPosition":"2824","Path":"2623 2724 2823 2822 2923 2924 3024 2925 2926 2825 2725 2624 2623"},{"Color":"Indigo","LabelPosition":"1633","Path":"1633"},{"Color":"Indigo","LabelPosition":"2224","Path":"2224"},{"Color":"Indigo","LabelPosition":"2328","Path":"2328"},{"Color":"Indigo","LabelPosition":"2428","Path":"2428"},{"Color":"Indigo","LabelPosition":"2832","Path":"2832"},{"Color":"Indigo","LabelPosition":"2920","Path":"2920"},{"Color":"Indigo","LabelPosition":"2930","Path":"2930"},{"Color":"Indigo","LabelPosition":"2939","Path":"2939"},{"Color":"Indigo","LabelPosition":"3119","Path":"3119"},{"Color":"Indigo","LabelPosition":"3133","Path":"3133"},{"Color":"Purple","LabelPosition":"2130","Path":"2130"},{"Color":"Purple","LabelPosition":"2331","Path":"2331"},{"Color":"Purple","LabelPosition":"2337","Path":"2337"},{"Color":"Purple","LabelPosition":"2438","Path":"2438"},{"Color":"Purple","LabelPosition":"2728","Path":"2728"},{"Color":"Purple","LabelPosition":"2821","Path":"2821"},{"Color":"Purple","LabelPosition":"2824","Path":"2824"},{"Color":"Purple","LabelPosition":"2831","Path":"2831"},{"Color":"Purple","LabelPosition":"2931","Path":"2931"},{"Color":"Purple","LabelPosition":"3037","Path":"3037"},{"Color":"Purple","LabelPosition":"3121","Path":"3121"}],"Routes":[{"Start":"2040","End":"2003","StartOffsetY":-1},{"Start":"2003","End":"1904"},{"Start":"1904","End":"1804"},{"Start":"1804","End":"1706"},{"Start":"2003","End":"2104"},{"Start":"1004","End":"1005"},{"Start":"1005","End":"1106"},{"Start":"1106","End":"1207"},{"Start":"1207","End":"1308"},{"Start":"1308","End":"1608"},{"Start":"1608","End":"1711"},{"Start":"1711","End":"2012"},{"Start":"1005","End":"0707"},{"Start":"0707","End":"0609"},{"Start":"0609","End":"0710"},{"Start":"0710","End":"0811"},{"Start":"0811","End":"1013"},{"Start":"2913","End":"2812"},{"Start":"2812","End":"2511"},{"Start":"2511","End":"2310"},{"Start":"2310","End":"2208"},{"Start":"2208","End":"2110"},{"Start":"2110","End":"2012"},{"Start":"2019","End":"2116"},{"Start":"2116","End":"2313"},{"Start":"2313","End":"2511"},{"Start":"2313","End":"2012"},{"Start":"1013","End":"1215"},{"Start":"1215","End":"1416"},{"Start":"1416","End":"1718"},{"Start":"1718","End":"2019"},{"Start":"2019","End":"2022"},{"Start":"2022","End":"2225"},{"Start":"2730","End":"2529"},{"Start":"2529","End":"2526"},{"Start":"2526","End":"2225"},{"Start":"2225","End":"2025"},{"Start":"2025","End":"1827"},{"Start":"1827","End":"1625"},{"Start":"1625","End":"1325"},{"Start":"1130","End":"0931"},{"Start":"0931","End":"0828"},{"Start":"0828","End":"0926"},{"Start":"0926","End":"1023"},{"Start":"1023","End":"1325"},{"Start":"1637","End":"1735"},{"Start":"1735","End":"1634"},{"Start":"1634","End":"1532"},{"Start":"1532","End":"1331"},{"Start":"1331","End":"1130"},{"Start":"1130","End":"1127"},{"Start":"1127","End":"1327"},{"Start":"1127","End":"1325"}]}