{"Tags":"Faraway DistantFringe","Names":[{"Text":"Suluru"}],"Credits":[],"X":48,"Y":25,"Products":[],"DataFile":{"Milieu":"M1105"},"Subsectors":[],"Allegiances":[{"Name":"Unknown","Code":"--"}],"Labels":[{"Hex":"1623","Color":"Gray","Size":"large","Wrap":false,"Text":"The Rift"},{"Hex":"3138","Color":"Gray","Size":"small","Wrap":false,"Text":"RSS\nSu3137"}],"Borders":[],"Regions":[{"Color":"DarkViolet","LabelPosition":"3121","Label":"Aiko Shoal","Path":"2226 2326 2325 2424 2525 2425 2426 2427 2428 2329 2229 2230 2229 2329 2328 2327 2226"},{"Color":"DarkViolet","LabelPosition":"2326","Label":"Lesser Suluran\nShoal","Path":"2735 2835 2935 2934 3033 3034 3135 3234 3235 3236 3137 3036 2936 2835 2735"},{"Color":"DarkViolet","LabelPosition":"3035","Label":"Great Suluran\nShoal","Path":"2922 3021 3020 3120 3121 3221 3122 3021 2922"}],"Routes":[]}