{"Tags":"Faraway DistantFringe","Names":[{"Text":"Wayland"}],"Credits":[],"X":49,"Y":29,"Products":[],"DataFile":{"Milieu":"M1105"},"Subsectors":[],"Allegiances":[{"Name":"Unknown","Code":"--"}],"Labels":[{"Hex":"1723","Color":"Gray","Size":"large","Wrap":false,"Text":"Great Void"},{"Hex":"1308","Color":"Gray","Size":"small","Wrap":false,"Text":"RSS\nWl1307"}],"Borders":[],"Regions":[{"Color":"DarkBlue","LabelPosition":"2633","Label":"Wisp\nCloud","Path":"2232 2332 2431 2532 2632 2633 2734 2735 2734 2633 2632 2532 2431 2332 2232"},{"Color":"DarkBlue","LabelPosition":"2939","Path":"2541 2640 2740 2840 2940 2939 2938 2837 2836 2936 3036 3037 3138 3139 3239 3339 3340 3341 3241 3141 3041 2941 2841 2741 2641 2541"}],"Routes":[]}